datasette_remote_actors.py
datasette_remote_actors-0.1a7.dist-info/licenses/LICENSE
datasette_remote_actors-0.1a7.dist-info/METADATA
datasette_remote_actors-0.1a7.dist-info/WHEEL
datasette_remote_actors-0.1a7.dist-info/entry_points.txt
datasette_remote_actors-0.1a7.dist-info/top_level.txt
datasette_remote_actors-0.1a7.dist-info/RECORD
