Metadata-Version: 2.4
Name: datasette-remote-actors
Version: 0.1a7
Summary: Datasette plugin for fetching details of actors from a remote endpoint
Author: Simon Willison
License-Expression: Apache-2.0
Project-URL: Homepage, https://github.com/datasette/datasette-remote-actors
Project-URL: Changelog, https://github.com/datasette/datasette-remote-actors/releases
Project-URL: Issues, https://github.com/datasette/datasette-remote-actors/issues
Project-URL: CI, https://github.com/datasette/datasette-remote-actors/actions
Classifier: Framework :: Datasette
License-File: LICENSE
Requires-Dist: datasette>=1.0a21
Requires-Dist: cachetools
Requires-Dist: httpx
Provides-Extra: test
Requires-Dist: pytest; extra == "test"
Requires-Dist: pytest-httpx; extra == "test"
Requires-Dist: pytest-asyncio; extra == "test"
Requires-Dist: datasette-profiles>=0.1a3; extra == "test"
Dynamic: license-file
